{
	"configurations" : 
	[
		{
			"directories" : 
			[
				{
					"build" : ".",
					"jsonFile" : "directory-.-Debug-f5ebdc15457944623624.json",
					"minimumCMakeVersion" : 
					{
						"string" : "3.23"
					},
					"projectIndex" : 0,
					"source" : ".",
					"targetIndexes" : 
					[
						0
					]
				}
			],
			"name" : "Debug",
			"projects" : 
			[
				{
					"directoryIndexes" : 
					[
						0
					],
					"name" : "Task7",
					"targetIndexes" : 
					[
						0
					]
				}
			],
			"targets" : 
			[
				{
					"directoryIndex" : 0,
					"id" : "Task7::@6890427a1f51a3e7e1df",
					"jsonFile" : "target-Task7-Debug-434709cd5cc54484d158.json",
					"name" : "Task7",
					"projectIndex" : 0
				}
			]
		}
	],
	"kind" : "codemodel",
	"paths" : 
	{
		"build" : "/home/doodox/Desktop/Contest/Sem_3/Task7/cmake-build-debug",
		"source" : "/home/doodox/Desktop/Contest/Sem_3/Task7"
	},
	"version" : 
	{
		"major" : 2,
		"minor" : 4
	}
}
